{
  "$schema": "../gen/schemas/desktop-schema.json",
  "identifier": "default",
  "description": "Capability for the main window",
  "windows": [
    "main",
    "station-editor"
  ],
  "permissions": [
    "core:default",
    "opener:default",
    "core:webview:allow-create-webview-window",
    "core:event:allow-emit",
    "core:event:allow-listen",
    "core:event:allow-unlisten",
    "dialog:default",
    "fs:default",
    "fs:allow-app-read-recursive",
    "fs:allow-app-write-recursive"
  ]
}